{
  "name": "Amy Padilla",
  "age": 34,
  "address": {
    "street": "Duwzi Turnpike",
    "city": "Ejhodzoh",
    "state": "NM",
    "zip": "55245"
  },
  "contact": {
    "phone": "(453) 378-8642",
    "servicePhone": "800694361"
  },
  "birthday": "1998-08-31T19:41:53.085Z",
  "ip": "120.185.207.241",
  "foo": "bar",
  "profile": {
    "about": "Ca enzefok edzep apwamar diupe balcekaz mavge wutiwo feemsev dilipoujo ci canli paverbak. Dibu hujo wikmun lutensaj uga gufo na cojiggot puzrak ade mehpu ik bofuwci wa pannus. Viwgi avoti apiomaceb monnog nogwa godtaffo jacfo sududec reihuh ro tubur baremohe zelul. Oczegak sef goporifow lus fipe ku wibu sazorzuv hampadisi hubewica cufo ujomvi gufhow kihurovev dus. Reg rojlofi nu ol ki cak maufe citujide duv ube nes ohtismu pibiv hu ku.",
    "bio": "Susiro ugi hu lucku ritamef fovce heoffot esogeju ciwfa fetloztim joopuca juw litbi novbossog wetrif kokit usrup giivima. Bo labitodi rak tocfe ahadoari amo voribma kerhu ol ni ekes efuirru ho kolubum. Uhsi de vev apuzenobi tu vi ogo jinbisapi faz metec reluk vica hidpobu. Ve ova hulophot gu ubuap ezu gufbicwoz agiisi vo lev ivnuc lutso otubu ipubuh gim."
  },
  "apiKey": "aae5f3e4bc765624d2ee6dc1b621f77ff6265645ce594db8dec2da914982649e",
  "currency": {
    "code": "BHD",
    "name": "Bahrain Dinar"
  }
}