{
  "name": "Luella Graves",
  "age": 28,
  "address": {
    "street": "Nogzo Ridge",
    "city": "Sihguti",
    "state": "VA",
    "zip": "00678"
  },
  "contact": {
    "phone": "(745) 796-2906",
    "servicePhone": "800516641"
  },
  "birthday": "1981-07-15T00:31:33.525Z",
  "ip": "58.43.128.77",
  "foo": "bar",
  "profile": {
    "about": "Ka eguco wedpujjil be of ecagow fef oksotel tongu cocid naga itfa. Vi zet kepebdu aboovesin uv cas tuwu ruohoig darjo jacoj rutopa etotkot buw kul mizew fo ek. Mozwufip laah hil ri iregib sog ziparwot tikzigho wogilut pi odifutzo ino.",
    "bio": "Bondawud hufif lipe git relafgap wacib be ajihaevo potakdib nanbof siffu obehihah mitjaf idakihij ec irwani og deffadit. Jes ro cakehodeb wu ki ludcepen fa vorzol ido kujez ono tad ocat ol takco laf. Enaof miztaldis wo lelwi ji mutime ker ovefuna ten citnep ip lasfojeta mopvaob. Duk dopkun iwu wooljaz zugassof zeketcit ubelor gu ga ludu careh zeukeuj dut nomowwuf haphebum dudweb vi. Otidevru bunob newud okuzi pugger zevo pijsoszun ogiholrep ruk sivoh ijikuvabu kobug mimvezuv ika zenudmev ciroc idu ti."
  },
  "apiKey": "25c420d60cb93a35b560617406653fc8d8eb567e88b085c8233c499d230a6be1",
  "currency": {
    "code": "TOP",
    "name": "Tonga Pa'anga"
  }
}